ID3Algorithm.py
buildTree.py
classify_data.py
node.py
decisiontree/ID3Algorithm.py
decisiontree/__init__.py
decisiontree/buildTree.py
decisiontree/classify_data.py
decisiontree/node.py
decision_tree_ID3_Algorithm-0.0.5.dist-info/LICENSE.txt
decision_tree_ID3_Algorithm-0.0.5.dist-info/METADATA
decision_tree_ID3_Algorithm-0.0.5.dist-info/WHEEL
decision_tree_ID3_Algorithm-0.0.5.dist-info/top_level.txt
decision_tree_ID3_Algorithm-0.0.5.dist-info/RECORD
